snakemold/__init__.py
snakemold-0.0.1.dist-info/LICENSE
snakemold-0.0.1.dist-info/METADATA
snakemold-0.0.1.dist-info/WHEEL
snakemold-0.0.1.dist-info/top_level.txt
snakemold-0.0.1.dist-info/RECORD
